django_qiyu_token/__init__.py
django_qiyu_token/admin/__init__.py
django_qiyu_token/admin/bearer.py
django_qiyu_token/admin/jwt_app.py
django_qiyu_token/admin/jwt_token.py
django_qiyu_token/apps.py
django_qiyu_token/locale/en/LC_MESSAGES/django.mo
django_qiyu_token/locale/en/LC_MESSAGES/django.po
django_qiyu_token/locale/zh/LC_MESSAGES/django.mo
django_qiyu_token/locale/zh/LC_MESSAGES/django.po
django_qiyu_token/migrations/0001_initial.py
django_qiyu_token/migrations/0002_alter_bearertokenmodel_user.py
django_qiyu_token/migrations/0003_jwtappmodel_jwttokenmodel.py
django_qiyu_token/migrations/__init__.py
django_qiyu_token/models/__init__.py
django_qiyu_token/models/bearer.py
django_qiyu_token/models/jwt_app.py
django_qiyu_token/models/jwt_token.py
django_qiyu_token/security.py
django_qiyu_token/tests.py
django_qiyu_token/views.py
django_qiyu_token-0.4.1.dist-info/LICENSE
django_qiyu_token-0.4.1.dist-info/WHEEL
django_qiyu_token-0.4.1.dist-info/METADATA
django_qiyu_token-0.4.1.dist-info/RECORD
