Metadata-Version: 2.1
Name: django-qiyu-token
Version: 0.4.1
Summary: Django Token Management APP
Home-page: https://oss.qiyutech.tech/
Author: dev
Author-email: dev@qiyutech.tech
Requires-Python: >=3.9,<3.11
Classifier: Programming Language :: Python :: 3
Classifier: Programming Language :: Python :: 3.9
Classifier: Programming Language :: Python :: 3.10
Requires-Dist: django (>=3.2,<4.2)
Requires-Dist: django-ninja (>=0.19,<0.20)
Requires-Dist: pyjwt[crypto] (>=2.1,<3.0)
Project-URL: Documentation, https://github.com/QiYuTechOrg/django-qiyu-token
Project-URL: Repository, https://github.com/QiYuTechOrg/django-qiyu-token
